pydriver/version.py
pydriver/__init__.py
pydriver/common/cconstants.h
pydriver/common/cconstants.pxd
pydriver/common/constants.pyd
pydriver/common/constants.pyx
pydriver/common/functions.pxd
pydriver/common/functions.pyd
pydriver/common/functions.pyx
pydriver/common/functions_include.pyx
pydriver/common/opencl_config.py
pydriver/common/structs.h
pydriver/common/structs.pxd
pydriver/common/__init__.py
pydriver/datasets/base.py
pydriver/datasets/kitti.py
pydriver/datasets/utils.py
pydriver/datasets/__init__.py
pydriver/detectors/detectors.pyd
pydriver/detectors/detectors.pyx
pydriver/detectors/vocabularies.pyd
pydriver/detectors/vocabularies.pyx
pydriver/detectors/__init__.py
pydriver/evaluation/evaluation.py
pydriver/evaluation/__init__.py
pydriver/features/base.pxd
pydriver/features/base.pyd
pydriver/features/base.pyx
pydriver/features/shot.pxd
pydriver/features/shot.pyd
pydriver/features/shot.pyx
pydriver/features/__init__.py
pydriver/geometry/geometry.pxd
pydriver/geometry/geometry.pyd
pydriver/geometry/geometry.pyx
pydriver/geometry/__init__.py
pydriver/keypoints/base.pyd
pydriver/keypoints/base.pyx
pydriver/keypoints/harris.pyd
pydriver/keypoints/harris.pyx
pydriver/keypoints/iss.pyd
pydriver/keypoints/iss.pyx
pydriver/keypoints/__init__.py
pydriver/pcl/pcl.pxd
pydriver/pcl/pcl.pyd
pydriver/pcl/pcl.pyx
pydriver/pcl/pcl_helper.pxd
pydriver/pcl/__init__.py
pydriver/pcl/pcl_helper/CMakeLists.txt
pydriver/pcl/pcl_helper/pcl_helper.cpp
pydriver/pcl/pcl_helper/pcl_helper.h
pydriver/pcl/pcl_helper/pcl_helper_exports.cpp
pydriver/pcl/pcl_helper/pcl_helper_exports.h
pydriver/pcl/pcl_helper/pcl_helper_imports.h
pydriver/pcl/pcl_helper/precompiled.cpp
pydriver/pcl/pcl_helper/precompiled.h
pydriver/pcl/pcl_helper/README.rst
pydriver/pcl/pcl_helper/lib/pcl_helper.dll
pydriver/pcl/pcl_helper/lib/pcl_helper.exp
pydriver/pcl/pcl_helper/lib/pcl_helper.lib
pydriver/preprocessing/preprocessing.pyd
pydriver-1.0.dist-info/DESCRIPTION.rst
pydriver-1.0.dist-info/METADATA
pydriver-1.0.dist-info/metadata.json
pydriver-1.0.dist-info/RECORD
pydriver-1.0.dist-info/top_level.txt
pydriver-1.0.dist-info/WHEEL
