Metadata-Version: 2.0
Name: pydriver
Version: 1.0
Summary: A framework for training and evaluating object detectors and classifiers in road traffic environment.
Home-page: http://github.com/lpltk/pydriver
Author: Leonard Plotkin
Author-email: git@leonard-plotkin.de
License: MIT
Platform: any
Classifier: Development Status :: 3 - Alpha
Classifier: Environment :: Console
Classifier: Intended Audience :: Science/Research
Classifier: License :: OSI Approved :: MIT License
Classifier: Operating System :: OS Independent
Classifier: Programming Language :: Python :: 2.7
Classifier: Programming Language :: Python :: 3
Classifier: Programming Language :: Cython
Classifier: Programming Language :: C++
Classifier: Topic :: Scientific/Engineering :: Image Recognition
Requires-Dist: numpy (>=1.8.1)
Requires-Dist: cython (>=0.22.1)
Requires-Dist: scipy (>=0.13.3)
Requires-Dist: scikit-image
Requires-Dist: scikit-learn
Requires-Dist: shapely
